pssecret_server/__init__.py
pssecret_server/cli.py
pssecret_server/fernet.py
pssecret_server/main.py
pssecret_server/models.py
pssecret_server/redis_db.py
pssecret_server/settings.py
pssecret_server/utils.py
pssecret_server-1.1.2.dist-info/LICENSE
pssecret_server-1.1.2.dist-info/METADATA
pssecret_server-1.1.2.dist-info/WHEEL
pssecret_server-1.1.2.dist-info/entry_points.txt
pssecret_server-1.1.2.dist-info/RECORD
