Metadata-Version: 2.3
Name: pssecret-server
Version: 1.1.2
Summary: API service for secrets sharing over network
Home-page: https://git.ivnglkv.me/root/pssecret-server
License: BSD-3-Clause
Author: Ivan Golikov
Author-email: root@ivnglkv.me
Requires-Python: >=3.11,<4.0
Classifier: Development Status :: 5 - Production/Stable
Classifier: Environment :: Web Environment
Classifier: Framework :: FastAPI
Classifier: Intended Audience :: Information Technology
Classifier: License :: OSI Approved :: BSD License
Classifier: Operating System :: OS Independent
Classifier: Programming Language :: Python :: 3
Classifier: Programming Language :: Python :: 3.11
Classifier: Programming Language :: Python :: 3.12
Classifier: Programming Language :: Python :: 3.13
Classifier: Topic :: Internet :: WWW/HTTP :: WSGI :: Application
Provides-Extra: hiredis
Requires-Dist: click (==8.1.8)
Requires-Dist: cryptography (>=44,<45)
Requires-Dist: fastapi[standard] (==0.115.6)
Requires-Dist: hiredis (==3.1.0) ; extra == "hiredis"
Requires-Dist: pydantic-settings (==2.7.0)
Requires-Dist: redis (==5.2.1)
Project-URL: Documentation, https://git.ivnglkv.me/root/pssecret-server/wiki
Project-URL: Repository, https://git.ivnglkv.me/root/pssecret-server
